[
  {
    "id": "0-A",
    "question": "Which is your favourite livery?",
    "scoring": "NA",
    "kh-response": "MCL",
    "hi-response": "ALP",
    "sh-response": "RBR",
    "kc-response": "AR",
    "tw-response": "MCL",
    "gh-response": "AR",
    "mg-response": "MCL"
  },
  {
    "id": "1-A",
    "question": "Who will win Constructor's Championship?",
    "scoring": "GP",
    "kh-response": "FER",
    "hi-response": "FER",
    "sh-response": "RBR",
    "kc-response": "MER",
    "tw-response": "RBR",
    "gh-response": "MER",
    "mg-response": "MER"
  },
  {
    "id": "1-B",
    "question": "What will the percentage of points difference be between first and second place in the Constructor's Championship?",
    "scoring": "VAL",
    "kh-response": 8,
    "hi-response": 15,
    "sh-response": 5,
    "kc-response": 3,
    "tw-response": 4,
    "gh-response": 6,
    "mg-response": 10
  },
  {
    "id": "1-C",
    "question": "Which team will come FIFTH in the Constructor's Championship?",
    "scoring": "GP",
    "kh-response": "WIL",
    "hi-response": "ALP",
    "sh-response": "AT",
    "kc-response": "AT",
    "tw-response": "ALP",
    "gh-response": "AT",
    "mg-response": "AM"
  },
  {
    "id": "1-D",
    "question": "Which team will come LAST in the Constructor's Championship?",
    "scoring": "GP",
    "kh-response": "HAA",
    "hi-response": "AT",
    "sh-response": "HAA",
    "kc-response": "HAA",
    "tw-response": "WIL",
    "gh-response": "WIL",
    "mg-response": "HAA"
  },
  {
    "id": "1-E",
    "question": "Who will WIN the Driver's Championship?",
    "scoring": "GP",
    "kh-response": "LEC",
    "hi-response": "HAM",
    "sh-response": "VER",
    "kc-response": "HAM",
    "tw-response": "VER",
    "gh-response": "HAM",
    "mg-response": "VER"
  },
  {
    "id": "1-F",
    "question": "What will the percentage of points difference be between first and second place in the Driver's Championship?",
    "scoring": "VAL",
    "kh-response": 5,
    "hi-response": 10,
    "sh-response": 5,
    "kc-response": 3,
    "tw-response": 6,
    "gh-response": 10,
    "mg-response": 5
  },
  {
    "id": "1-G",
    "question": "Who will come TENTH in the Driver's Championship?",
    "scoring": "GP",
    "kh-response": "ALB",
    "hi-response": "OCO",
    "sh-response": "ALO",
    "kc-response": "ALO",
    "tw-response": "OCO",
    "gh-response": "VET",
    "mg-response": "GAS"
  },
  {
    "id": "1-H",
    "question": "Who will come LAST in the Driver's Championship?",
    "scoring": "GP",
    "kh-response": "ZHO",
    "hi-response": "ZHO",
    "sh-response": "ZHO",
    "kc-response": "ZHO",
    "tw-response": "LAT",
    "gh-response": "LAT",
    "mg-response": "ZHO"
  },
  {
    "id": "1-I",
    "question": "Which team will have the highest repair cost, and WIN the Destructors Championship?",
    "scoring": "GP",
    "kh-response": "AT",
    "hi-response": "RBR",
    "sh-response": "AM",
    "kc-response": "HAA",
    "tw-response": "AR",
    "gh-response": "WIL",
    "mg-response": "AR"
  },
  {
    "id": "1-J",
    "question": "Which team will have the lowest repair cost, and come LAST in the Destructors Championship?",
    "scoring": "GP",
    "kh-response": "MER",
    "hi-response": "WIL",
    "sh-response": "MER",
    "kc-response": "MCL",
    "tw-response": "AT",
    "gh-response": "ALP",
    "mg-response": "MER"
  },
  {
    "id": "1-K",
    "question": "Which driver will cause the most cost in repairs, and WIN the Destructors Championship?",
    "scoring": "GP",
    "kh-response": "TSU",
    "hi-response": "VER",
    "sh-response": "STR",
    "kc-response": "STR",
    "tw-response": "ZHO",
    "gh-response": "ZHO",
    "mg-response": "LAT"
  },
  {
    "id": "1-L",
    "question": "Which driver will cause the least in repair cost, and come LAST in the Destructors Championship?",
    "scoring": "GP",
    "kh-response": "HAM",
    "hi-response": "VET",
    "sh-response": "HAM",
    "kc-response": "HAM",
    "tw-response": "GAS",
    "gh-response": "ALO",
    "mg-response": "HAM"
  },
  {
    "id": "2-A",
    "question": "Which team will have the MOST podiums?",
    "scoring": "GP",
    "kh-response": "MER",
    "hi-response": "FER",
    "sh-response": "MER",
    "kc-response": "MER",
    "tw-response": "MER",
    "gh-response": "MER",
    "mg-response": "MER"
  },
  {
    "id": "2-B",
    "question": "Which team will have the FASTEST pitstop?",
    "scoring": "GP",
    "kh-response": "RBR",
    "hi-response": "RBR",
    "sh-response": "RBR",
    "kc-response": "RBR",
    "tw-response": "RBR",
    "gh-response": "RBR",
    "mg-response": "RBR"
  },
  {
    "id": "2-C",
    "question": "Which team will have the MOST DNFs? (specific to Sunday races)",
    "scoring": "GP",
    "kh-response": "MCL",
    "hi-response": "MCL",
    "sh-response": "ALP",
    "kc-response": "HAA",
    "tw-response": "AR",
    "gh-response": "WIL",
    "mg-response": "FER"
  },
  {
    "id": "2-D",
    "question": "Chose TWO teams - every time one of their drivers make it to Q2, you LOSE 1 point",
    "scoring": "MISC-1",
    "kh-response": "AR,HAA",
    "hi-response": "AR,HAA",
    "sh-response": "HAA,WIL",
    "kc-response": "AR,HAA",
    "tw-response": "AR,WIL",
    "gh-response": "AR,WIL",
    "mg-response": "AR,HAA"
  },
  {
    "id": "2-E",
    "question": "Which team will have the FIRST mechanical failure in the season during a RACE?",
    "scoring": "GP",
    "kh-response": "MCL",
    "hi-response": "AR",
    "sh-response": "AM",
    "kc-response": "WIL",
    "tw-response": "WIL",
    "gh-response": "WIL",
    "mg-response": "WIL"
  },
  {
    "id": "2-F",
    "question": "Which team will have the LONGEST pitstop in the first race of the season?",
    "scoring": "GP",
    "kh-response": "FER",
    "hi-response": "FER",
    "sh-response": "HAA",
    "kc-response": "AR",
    "tw-response": "HAA",
    "gh-response": "HAA",
    "mg-response": "AT"
  },
  {
    "id": "2-G",
    "question": "Pick THREE races of the season YOU think the AlphaTauri drivers will do the BEST at.",
    "scoring": "MISC-2",
    "kh-response": "BAH,BAK,MZA",
    "hi-response": "MIA,MZA,RUS",
    "sh-response": "EMR,MIA,BAK",
    "kc-response": "HUN,SPA,NED",
    "tw-response": "BAR,BAK,YMC",
    "gh-response": "BAR,RUS,YMC",
    "mg-response": "BAH,MIA,CAN"
  },
  {
    "id": "2-H",
    "question": "Pick a team - every time one of their drivers finishes 16th OR LOWER, you score points.",
    "scoring": "MISC-3",
    "kh-response": "AR",
    "hi-response": "AR",
    "sh-response": "WIL",
    "kc-response": "HAA",
    "tw-response": "WIL",
    "gh-response": "WIL",
    "mg-response": "HAA"
  },
  {
    "id": "2-G",
    "question": "Which team will be the biggest winner compared to 2021?",
    "scoring": "GP",
    "kh-response": "WIL",
    "hi-response": "WIL",
    "sh-response": "MCL",
    "kc-response": "AT",
    "tw-response": "HAA",
    "gh-response": "HAA",
    "mg-response": "FER"
  },
  {
    "id": "3-A",
    "question": "Who will have the most laps led throughout the season?",
    "scoring": "GP",
    "kh-response": "LEC",
    "hi-response": "HAM",
    "sh-response": "VER",
    "kc-response": "VER",
    "tw-response": "VER",
    "gh-response": "HAM",
    "mg-response": "HAM"
  },
  {
    "id": "3-B",
    "question": "Which drivers will receive the \"Driver of the Day\" award?",
    "scoring": "MISC-4",
    "kh-response": "GAS,HAM,LEC,NOR,RUS,SAI,VER,VET",
    "hi-response": "HAM,LEC,NOR,RIC,RUS,SAI,VER,VET",
    "sh-response": "ALB,ALO,GAS,HAM,LEC,NOR,OCO,PER,RIC,RUS,MSC,VER,VET",
    "kc-response": "ALO,HAM,LEC,NOR,RUS,VER",
    "tw-response": "ALO,HAM,LEC,NOR,RIC,RUS,MSC,VER",
    "gh-response": "ALO,HAM,LEC,NOR,PER,RUS,SAI,MSC,VER,VET",
    "mg-response": "HAM,NOR,RUS"
  },
  {
    "id": "3-C",
    "question": "Select ONE track for Sainz, Stroll, Tsunoda, Alonso, and Bottas.",
    "scoring": "MISC-5",
    "kh-response": "SAI-NED,STR-CAN,TSU-BAH,ALO-BAR,BOT-SPA",
    "hi-response": "SAI-MZA,STR-CAN,TSU-JPN,ALO-BAR,BOT-RUS",
    "sh-response": "SAI-MON,STR-MIA,TSU-EMR,ALO-AUS,BOT-SAA",
    "kc-response": "SAI-AUS,STR-BAR,TSU-MIA,ALO-SAA,BOT-EMR",
    "tw-response": "SAI-BAR,STR-CAN,TSU-JPN,ALO-HUN,BOT-SPA",
    "gh-response": "SAI-BAH,STR-CAN,TSU-JPN,ALO-BAR,BOT-SAA",
    "mg-response": "SAI-BAR,STR-HUN,TSU-JPN,ALO-MZA,BOT-SPA"
  },
  {
    "id": "3-D",
    "question": "Pick THREE drivers who will come the \"best of the rest\" the most.",
    "scoring": "MISC-6",
    "kh-response": "GAS,PER,SAI",
    "hi-response": "GAS,NOR,VER",
    "sh-response": "GAS,NOR,RUS",
    "kc-response": "NOR,PER,RIC",
    "tw-response": "LEC,NOR,RUS",
    "gh-response": "LEC,NOR,PER",
    "mg-response": "LEC,PER,RUS"
  },
  {
    "id": "3-E",
    "question": "Who are going to be the Q2 specialists?",
    "scoring": "MISC-7",
    "kh-response": "ALB,ALO,TSU,VET",
    "hi-response": "ALB,ALO,STR,TSU",
    "sh-response": "ALB,MAG,MSC,TSU",
    "kc-response": "BOT,LAT,STR,VET",
    "tw-response": "BOT,MSC,STR,TSU",
    "gh-response": "BOT,MAG,MSC,TSU",
    "mg-response": "ALB,MAG,SAI,VET"
  },
  {
    "id": "3-F",
    "question": "Pick all the drivers you think will make the podium.",
    "scoring": "MISC-8",
    "kh-response": "GAS,HAM,LEC,NOR,PER,RIC,RUS,SAI,VER",
    "hi-response": "GAS,HAM,LEC,NOR,RIC,RUS,SAI,VER,VET",
    "sh-response": "GAS,HAM,LEC,NOR,PER,RIC,RUS,SAI,VER",
    "kc-response": "GAS,HAM,LEC,NOR,PER,RIC,RUS,SAI,VER",
    "tw-response": "ALO,GAS,HAM,LEC,NOR,PER,RIC,RUS,SAI,VER",
    "gh-response": "ALO,GAS,HAM,LEC,NOR,PER,RIC,RUS,SAI,VER",
    "mg-response": "HAM,NOR,PER,RUS,VER,VET"
  },
  {
    "id": "3-G",
    "question": "Which driver will get the most grid penalties?",
    "scoring": "MISC-9",
    "kh-response": "RIC",
    "hi-response": "ZHO",
    "sh-response": "MAG",
    "kc-response": "MSC",
    "tw-response": "ZHO",
    "gh-response": "ZHO",
    "mg-response": "VER"
  },
  {
    "id": "3-H",
    "question": "Which drivers will be the most mischievous and get the most license point penalties?",
    "scoring": "MISC-10",
    "kh-response": "LEC,MAG",
    "hi-response": "VER,ZHO",
    "sh-response": "STR,TSU",
    "kc-response": "MAG,ZHO",
    "tw-response": "STR,ZHO",
    "gh-response": "STR,ZHO",
    "mg-response": "HAM,VER"
  },
  {
    "id": "3-I",
    "question": "Select the drivers who you think will NOT be on the grid in 2023.",
    "scoring": "MISC-11",
    "star": "MG",
    "kh-response": "ALO,MAG,TSU,ZHO",
    "hi-response": "HAM,VET,ZHO",
    "sh-response": "LAT,MAG",
    "kc-response": "MAG,VET,ZHO",
    "tw-response": "ALO,LAT,MAG",
    "gh-response": "ALO,MAG",
    "mg-response": "ALB,TSU,ZHO"
  },
  {
    "id": "3-J",
    "question": "Who will be the biggest loser compared to 2021?",
    "scoring": "GP",
    "kh-response": "BOT",
    "hi-response": "BOT",
    "sh-response": "BOT",
    "kc-response": "BOT",
    "tw-response": "BOT",
    "gh-response": "BOT",
    "mg-response": "BOT"
  },
  {
    "id": "3-K",
    "question": "Pick THREE races of the season YOU think Leclerc will perform the BEST at.",
    "scoring": "MISC-12",
    "kh-response": "BAK,NED,MZA",
    "hi-response": "MON,SPA,MZA",
    "sh-response": "EMR,BAR,CTA",
    "kc-response": "EMR,GBR,MZA",
    "tw-response": "BAH,MON,MZA",
    "gh-response": "BAH,MON,MZA",
    "mg-response": "BAR,MON,CPR"
  },
  {
    "id": "4-A",
    "question": "Which team will score the most points at the Baku circuit?",
    "scoring": "GP",
    "kh-response": "FER",
    "hi-response": "RBR",
    "sh-response": "RBR",
    "kc-response": "RBR",
    "tw-response": "FER",
    "gh-response": "RBR",
    "mg-response": "MER"
  },
  {
    "id": "4-B",
    "question": "How many safety cars will there be during the Sunday races?",
    "scoring": "VAL",
    "kh-response": 15,
    "hi-response": 15,
    "sh-response": 20,
    "kc-response": 17,
    "tw-response": 18,
    "gh-response": 20,
    "mg-response": 16
  },
  {
    "id": "4-C",
    "question": "How many Virtual Safety Cars (VSCs) will there be during the Sunday races?",
    "scoring": "VAL",
    "kh-response": 10,
    "hi-response": 5,
    "sh-response": 9,
    "kc-response": 9,
    "tw-response": 7,
    "gh-response": 10,
    "mg-response": 10
  },
  {
    "id": "4-D",
    "question": "How many Red Flags will there be during the Sunday races?",
    "scoring": "VAL",
    "kh-response": 4,
    "hi-response": 5,
    "sh-response": 8,
    "kc-response": 7,
    "tw-response": 8,
    "gh-response": 9,
    "mg-response": 3
  },
  {
    "id": "4-E",
    "question": "How many wet sessions will there be?",
    "scoring": "VAL",
    "kh-response": 20,
    "hi-response": 15,
    "sh-response": 15,
    "kc-response": 20,
    "tw-response": 15,
    "gh-response": 20,
    "mg-response": 20
  },
  {
    "id": "4-F",
    "question": "Which race will be voted the fan favourite?",
    "scoring": "GP",
    "kh-response": "MZA",
    "hi-response": "SPA",
    "sh-response": "MZA",
    "kc-response": "MON",
    "tw-response": "SPA",
    "gh-response": "MZA",
    "mg-response": "MIA"
  },
  {
    "id": "4-G",
    "question": "Pick THREE drivers you think will perform the best at the MIAMI circuit.",
    "scoring": "MISC-13",
    "kh-response": "HAM,LEC,VER",
    "hi-response": "HAM,PER,RUS",
    "sh-response": "HAM,RUS,VER",
    "kc-response": "HAM,RUS,VER",
    "tw-response": "NOR,SAI,VER",
    "gh-response": "HAM,SAI,VER",
    "mg-response": "HAM,PER,VER"
  },
  {
    "id": "4-H",
    "question": "Pick FOUR tracks you think there will be the MOST DNFs during the race.",
    "scoring": "MISC-13",
    "kh-response": "BAH,SAA,EMR,MON",
    "hi-response": "SAA,BAK,JPN,YMC",
    "sh-response": "BAH,MIA,MON,SIN",
    "kc-response": "BAH,AUS,BAK,SPA",
    "tw-response": "SAA,MON,BAK,SPA",
    "gh-response": "SAA,MON,SPA,JPN",
    "mg-response": "RBR,CPR,SPA,RUS"
  },
  {
    "id": "5-A",
    "question": "All teams will score points.",
    "scoring": "BOOL",
    "kh-response": true,
    "hi-response": true,
    "sh-response": true,
    "kc-response": false,
    "tw-response": false,
    "gh-response": true,
    "mg-response": true
  },
  {
    "id": "5-B",
    "question": "Russell outscores Perez.",
    "scoring": "BOOL",
    "kh-response": true,
    "hi-response": true,
    "sh-response": true,
    "kc-response": true,
    "tw-response": true,
    "gh-response": true,
    "mg-response": false
  },
  {
    "id": "5-C",
    "question": "The winning constructor takes 10 or fewer race wins.",
    "scoring": "BOOL",
    "kh-response": true,
    "hi-response": true,
    "sh-response": false,
    "kc-response": false,
    "tw-response": true,
    "gh-response": true,
    "mg-response": false
  },
  {
    "id": "5-D",
    "question": "Team in 10th place after Race 10 will still be 10th by the end of the season.",
    "scoring": "BOOL",
    "kh-response": true,
    "hi-response": false,
    "sh-response": false,
    "kc-response": false,
    "tw-response": false,
    "gh-response": false,
    "mg-response": true
  },
  {
    "id": "5-E",
    "question": "The Formula 2 Driver Champion gets a 2023 seat.",
    "scoring": "BOOL",
    "kh-response": true,
    "hi-response": false,
    "sh-response": false,
    "kc-response": true,
    "tw-response": false,
    "gh-response": false,
    "mg-response": true
  },
  {
    "id": "5-F",
    "question": "Select all the bold predictions you think will come true!",
    "scoring": "BOOL-LIST",
    "kh-response": "0,3,4,7,8,11,12",
    "hi-response": "0,3,4,8,9",
    "sh-response": "4,9,10,11,12",
    "kc-response": "3,4,8,9,11",
    "tw-response": "2,3,4,9,12",
    "gh-response": "0,3,9,10,12",
    "mg-response": "9,10"
  },
  {
    "id": "6-A",
    "question": "Mercedes vs Red Bull",
    "scoring": "VS",
    "kh-response": "MER",
    "hi-response": "MER",
    "sh-response": "MER",
    "kc-response": "MER",
    "tw-response": "RBR",
    "gh-response": "MER",
    "mg-response": "RBR"
  },
  {
    "id": "6-B",
    "question": "Ferrari vs McLaren",
    "scoring": "VS",
    "kh-response": "FER",
    "hi-response": "FER",
    "sh-response": "MCL",
    "kc-response": "FER",
    "tw-response": "FER",
    "gh-response": "FER",
    "mg-response": "FER"
  },
  {
    "id": "6-C",
    "question": "Alpine vs AlphaTauri",
    "scoring": "VS",
    "kh-response": "AT",
    "hi-response": "ALP",
    "sh-response": "AT",
    "kc-response": "AT",
    "tw-response": "ALP",
    "gh-response": "AT",
    "mg-response": "AT"
  },
  {
    "id": "6-D",
    "question": "Aston Martin vs Williams",
    "scoring": "VS",
    "kh-response": "WIL",
    "hi-response": "WIL",
    "sh-response": "AM",
    "kc-response": "AM",
    "tw-response": "AM",
    "gh-response": "AM",
    "mg-response": "AM"
  },
  {
    "id": "6-E",
    "question": "Alfa Romeo vs Haas",
    "scoring": "VS",
    "kh-response": "HAA",
    "hi-response": "HAA",
    "sh-response": "AR",
    "kc-response": "AR",
    "tw-response": "HAA",
    "gh-response": "HAA",
    "mg-response": "AR"
  },
  {
    "id": "6-F",
    "question": "Mercedes Drivers Head to Head",
    "scoring": "H2H",
    "kh-response": "RUS,HAM",
    "hi-response": "HAM,HAM",
    "sh-response": "HAM,HAM",
    "kc-response": "HAM,HAM",
    "tw-response": "HAM,HAM",
    "gh-response": "HAM,HAM",
    "mg-response": "HAM,HAM"
  },
  {
    "id": "6-G",
    "question": "Red Bull Drivers Head to Head",
    "scoring": "H2H",
    "kh-response": "VER,VER",
    "hi-response": "VER,VER",
    "sh-response": "VER,VER",
    "kc-response": "VER,VER",
    "tw-response": "VER,VER",
    "gh-response": "VER,VER",
    "mg-response": "VER,VER"
  },
  {
    "id": "6-H",
    "question": "Ferrari Drivers Head to Head",
    "scoring": "H2H",
    "kh-response": "LEC,SAI",
    "hi-response": "SAI,SAI",
    "sh-response": "LEC,SAI",
    "kc-response": "LEC,LEC",
    "tw-response": "LEC,SAI",
    "gh-response": "LEC,SAI",
    "mg-response": "LEC,LEC"
  },
  {
    "id": "6-I",
    "question": "McLaren Drivers Head to Head",
    "scoring": "H2H",
    "kh-response": "NOR,NOR",
    "hi-response": "NOR,NOR",
    "sh-response": "NOR,NOR",
    "kc-response": "NOR,NOR",
    "tw-response": "NOR,NOR",
    "gh-response": "NOR,NOR",
    "mg-response": "RIC,RIC"
  },
  {
    "id": "6-J",
    "question": "Alpine Drivers Head to Head",
    "scoring": "H2H",
    "kh-response": "OCO,ALO",
    "hi-response": "ALO,ALO",
    "sh-response": "ALO,ALO",
    "kc-response": "ALO,ALO",
    "tw-response": "ALO,OCO",
    "gh-response": "ALO,OCO",
    "mg-response": "OCO,ALO"
  },
  {
    "id": "6-K",
    "question": "AlphaTauri Drivers Head to Head",
    "scoring": "H2H",
    "kh-response": "GAS,GAS",
    "hi-response": "GAS,GAS",
    "sh-response": "GAS,GAS",
    "kc-response": "GAS,GAS",
    "tw-response": "GAS,GAS",
    "gh-response": "GAS,GAS",
    "mg-response": "TSU,GAS"
  },
  {
    "id": "6-L",
    "question": "Aston Martin Drivers Head to Head",
    "scoring": "H2H",
    "kh-response": "VET,VET",
    "hi-response": "STR,VET",
    "sh-response": "VET,VET",
    "kc-response": "STR,VET",
    "tw-response": "VET,VET",
    "gh-response": "VET,VET",
    "mg-response": "VET,VET"
  },
  {
    "id": "6-M",
    "question": "Alfa Romeo Drivers Head to Head",
    "scoring": "H2H",
    "kh-response": "BOT,BOT",
    "hi-response": "BOT,BOT",
    "sh-response": "BOT,BOT",
    "kc-response": "BOT,BOT",
    "tw-response": "BOT,BOT",
    "gh-response": "BOT,BOT",
    "mg-response": "BOT,BOT"
  },
  {
    "id": "6-N",
    "question": "Williams Drivers Head to Head",
    "scoring": "H2H",
    "kh-response": "ALB,ALB",
    "hi-response": "ALB,ALB",
    "sh-response": "ALB,ALB",
    "kc-response": "ALB,ALB",
    "tw-response": "LAT,ALB",
    "gh-response": "ALB,ALB",
    "mg-response": "ALB,ALB"
  },
  {
    "id": "6-O",
    "question": "Haas Drivers Head to Head",
    "scoring": "H2H",
    "kh-response": "MSC,MAG",
    "hi-response": "MAG,MAG",
    "sh-response": "MAG,MSC",
    "kc-response": "MSC,MSC",
    "tw-response": "MSC,MAG",
    "gh-response": "MSC,MAG",
    "mg-response": "MSC,MAG"
  },
  {
    "id": "7-1",
    "question": "Constructor Championship Order",
    "scoring": "ORDER",
    "kh-response": "FER,MER,RBR,MCL,WIL,AT,AM,ALP,HAA,AR",
    "hi-response": "FER,MER,RBR,MCL,ALP,AT,AM,WIL,AR,HAA",
    "sh-response": "RBR,MER,MCL,FER,AT,ALP,AM,AR,WIL,HAA",
    "kc-response": "MER,RBR,FER,MCL,AT,ALP,AM,WIL,AR,HAA",
    "tw-response": "MER,RBR,FER,MCL,ALP,AT,AM,AR,HAA,WIL",
    "gh-response": "MER,RBR,FER,MCL,ALP,AT,AM,AR,HAA,WIL",
    "mg-response": "MER,RBR,FER,MCL,AM,AT,AR,ALP,WIL,HAA"
  },
  {
    "id": "7-2",
    "question": "Driver Championship Order",
    "scoring": "ORDER",
    "star": "TW",
    "kh-response": "LEC,HAM,VER,SAI,RUS,NOR,PER,GAS,RIC,ALB,ALO,VET,TSU,OCO,STR,LAT,BOT,MSC,MAG,ZHO",
    "hi-response": "HAM,SAI,VER,LEC,RUS,NOR,PER,GAS,RIC,OCO,ALO,TSU,VET,ALB,STR,BOT,LAT,MAG,MSC,ZHO",
    "sh-response": "VER,HAM,RUS,PER,SAI,NOR,RIC,LEC,GAS,ALO,BOT,VET,OCO,TSU,ALB,STR,MAG,MSC,LAT,ZHO",
    "kc-response": "HAM,VER,RUS,LEC,SAI,PER,NOR,RIC,GAS,ALO,VET,TSU,OCO,ALB,BOT,STR,LAT,MAG,MSC,ZHO",
    "tw-response": "VER,HAM,RUS,LEC,NOR,PER,SAI,RIC,ALO,GAS,OCO,TSU,VET,BOT,STR,MAG,MSC,LAT,ALB,ZHO",
    "gh-response": "HAM,VER,RUS,PER,LEC,NOR,SAI,GAS,ALO,RIC,VET,STR,OCO,TSU,MSC,MAG,ALB,BOT,ZHO,LAT",
    "mg-response": "VER,HAM,PER,RUS,SAI,NOR,LEC,RIC,GAS,VET,ALB,ALO,BOT,LAT,OCO,MAG,STR,TSU,ZHO,MSC"
  }
]
